fauxai/__init__.py
fauxai/cli.py
fauxai/clients/__init__.py
fauxai/clients/anthropic.py
fauxai/clients/cohere.py
fauxai/clients/mistralai.py
fauxai/clients/openai.py
fauxai/constants.py
fauxai/server/__init__.py
fauxai/server/main.py
fauxai/server/models.py
fauxai/server/responses.py
fauxai-0.1.0.dist-info/METADATA
fauxai-0.1.0.dist-info/WHEEL
fauxai-0.1.0.dist-info/entry_points.txt
fauxai-0.1.0.dist-info/RECORD
