Metadata-Version: 2.1
Name: fauxai
Version: 0.1.0
Summary: Mock clients for your favorite LLM APIs
License: MIT
Author: Anibal Angulo
Author-email: ajcardoza2000@gmail.com
Requires-Python: >=3.12,<4.0
Classifier: License :: OSI Approved :: MIT License
Classifier: Programming Language :: Python :: 3
Classifier: Programming Language :: Python :: 3.12
Requires-Dist: fastapi[standard] (>=0.111.0,<0.112.0)
Requires-Dist: pydantic (>=2.7.4,<3.0.0)
Requires-Dist: pytest-asyncio (>=0.23.7,<0.24.0)
Requires-Dist: typer[all] (>=0.12.3,<0.13.0)
